{"primaryContentSections":[{"kind":"content","content":[{"level":3,"text":"Actual version release","anchor":"Actual-version-release","type":"heading"},{"level":2,"text":"Summary","anchor":"Summary","type":"heading"},{"inlineContent":[{"type":"codeVoice","code":"2.0.0-beta"},{"type":"text","text":" is a major SDK update focused on connection stability, diagnostics and NTRIP resilience."}],"type":"paragraph"},{"level":2,"text":"Breaking Changes","anchor":"Breaking-Changes","type":"heading"},{"items":[{"content":[{"inlineContent":[{"text":"Legacy peripheral logging APIs are no longer available.","type":"text"}],"type":"paragraph"}]},{"content":[{"inlineContent":[{"text":"NTRIP connection state has new reconnect cases, so exhaustive ","type":"text"},{"type":"codeVoice","code":"switch"},{"text":" statements may need updates.","type":"text"}],"type":"paragraph"}]},{"content":[{"inlineContent":[{"text":"Single Point measurement errors have new cases, so exhaustive ","type":"text"},{"type":"codeVoice","code":"switch"},{"text":" statements may need updates.","type":"text"}],"type":"paragraph"}]}],"type":"unorderedList"},{"level":2,"text":"Migration Guide","anchor":"Migration-Guide","type":"heading"},{"level":3,"text":"Logging","anchor":"Logging","type":"heading"},{"inlineContent":[{"type":"text","text":"1.0.8:"}],"type":"paragraph"},{"code":["let peripheral = try Vigram.peripheral(","    cbPeripheral,","    log: logURL,","    configuration: configuration",")"],"syntax":"swift","type":"codeListing"},{"code":["let logger = try Vigram.peripheralLogger(for: logURL)","","let peripheral = Vigram.peripheral(","    cbPeripheral,","    logger: logger,","    configuration: configuration",")"],"syntax":"swift","type":"codeListing"},{"inlineContent":[{"type":"text","text":"2.0.0-beta:"}],"type":"paragraph"},{"code":["try Vigram.Logger(url: logURL, mode: .basic)","","let peripheral = Vigram.peripheral(","    cbPeripheral,","    configuration: configuration",")"],"syntax":"swift","type":"codeListing"},{"inlineContent":[{"type":"text","text":"For deeper support diagnostics."}],"type":"paragraph"},{"code":["try Vigram.Logger(url: logURL, mode: .diagnostic)"],"syntax":"swift","type":"codeListing"},{"inlineContent":[{"type":"text","text":"Notes:"}],"type":"paragraph"},{"items":[{"content":[{"inlineContent":[{"text":"Logs are written as JSON Lines.","type":"text"}],"type":"paragraph"}]},{"content":[{"inlineContent":[{"text":"Available modes are ","type":"text"},{"type":"codeVoice","code":"basic"},{"text":" and ","type":"text"},{"type":"codeVoice","code":"diagnostic"},{"text":".","type":"text"}],"type":"paragraph"}]},{"content":[{"inlineContent":[{"text":"Tokens, NTRIP credentials and private device identifiers are redacted automatically.","type":"text"}],"type":"paragraph"}]}],"type":"unorderedList"},{"level":3,"text":"NTRIP Reconnect","anchor":"NTRIP-Reconnect","type":"heading"},{"inlineContent":[{"type":"text","text":"1.0.8:"}],"type":"paragraph"},{"code":["let gpsService = Vigram.gpsService(","    peripheral: peripheral,","    bluetoothService: bluetoothService,","    correctionTask: ntripTask",")"],"syntax":"swift","type":"codeListing"},{"inlineContent":[{"type":"text","text":"2.0.0-beta:"}],"type":"paragraph"},{"code":["let gpsService = Vigram.gpsService(","    peripheral: peripheral,","    bluetoothService: bluetoothService,","    correctionTask: ntripTask,","    automaticallyReconnectNtrip: true",")"],"syntax":"swift","type":"codeListing"},{"inlineContent":[{"type":"codeVoice","code":"automaticallyReconnectNtrip"},{"type":"text","text":" is enabled by default."},{"type":"text","text":" "},{"type":"text","text":"To disable it."}],"type":"paragraph"},{"code":["let gpsService = Vigram.gpsService(","    peripheral: peripheral,","    bluetoothService: bluetoothService,","    correctionTask: ntripTask,","    automaticallyReconnectNtrip: false",")"],"syntax":"swift","type":"codeListing"},{"inlineContent":[{"type":"text","text":"Apps that observe "},{"type":"codeVoice","code":"ntripTask.ntripState"},{"type":"text","text":" may receive new reconnect states."}],"type":"paragraph"},{"code":["case .reconnectScheduled(attempt: Int, maxAttempts: Int, delay: TimeInterval)","case .reconnecting(attempt: Int, maxAttempts: Int)","case .reconnectRestored(attempt: Int)","case .reconnectFailed(maxAttempts: Int, lastError: Error?)"],"syntax":"swift","type":"codeListing"},{"level":3,"text":"NTRIP HTTPS","anchor":"NTRIP-HTTPS","type":"heading"},{"inlineContent":[{"type":"text","text":"1.0.8:"}],"type":"paragraph"},{"code":["let information = NtripConnectionInformation(","    hostname: \"caster.example.com\",","    port: 2101,","    username: username,","    password: password",")"],"syntax":"swift","type":"codeListing"},{"inlineContent":[{"type":"text","text":"2.0.0-beta:"}],"type":"paragraph"},{"code":["let information = NtripConnectionInformation(","    hostname: \"caster.example.com\",","    port: 2101,","    username: username,","    password: password,","    forceHTTPSconnection: true,","    forceHTTPSMountpointsConnection: true",")"],"syntax":"swift","type":"codeListing"},{"inlineContent":[{"type":"text","text":"Notes:"}],"type":"paragraph"},{"items":[{"content":[{"inlineContent":[{"type":"codeVoice","code":"forceHTTPSMountpointsConnection"},{"text":" controls mountpoint\/sourcetable loading.","type":"text"}],"type":"paragraph"}]},{"content":[{"inlineContent":[{"type":"codeVoice","code":"forceHTTPSconnection"},{"text":" controls the correction stream.","type":"text"}],"type":"paragraph"}]},{"content":[{"inlineContent":[{"text":"Mountpoint loading has its own timeout: ","type":"text"},{"type":"codeVoice","code":"Configuration.ntripMountpointsTimeout"},{"text":".","type":"text"}],"type":"paragraph"}]}],"type":"unorderedList"},{"level":3,"text":"Single Point Errors","anchor":"Single-Point-Errors","type":"heading"},{"inlineContent":[{"type":"text","text":"1.0.8:"}],"type":"paragraph"},{"code":["if case .failure(let error) = completion {","    \/\/ show generic measurement error","}"],"syntax":"swift","type":"codeListing"},{"inlineContent":[{"type":"text","text":"2.0.0-beta:"}],"type":"paragraph"},{"code":["if case .failure(let error) = completion {","    switch error as? SinglePointRecordingError {","    case .noMeasurementsCollected:","        \/\/ no data collected","    case .noValidMeasurements:","        \/\/ data did not pass validation","    case .insufficientValidMeasurements:","        \/\/ not enough valid data","    case .horizontalAccuracyIsTooHigh:","        \/\/ horizontal accuracy is too high","    case .verticalAccuracyIsTooHigh:","        \/\/ vertical accuracy is too high","    case .altitudeDifferenceIsTooHigh:","        \/\/ altitude difference is too high","    case .laserMeasurementsIsBadQuality:","        \/\/ bad laser quality","    case .measurementAlreadyRunning:","        \/\/ another measurement is running","    case .measurementCancelled:","        \/\/ cancelled by user","    default:","        \/\/ fallback","    }","}"],"syntax":"swift","type":"codeListing"},{"level":2,"text":"Added","anchor":"Added","type":"heading"},{"items":[{"content":[{"inlineContent":[{"text":"Structured support logging through ","type":"text"},{"type":"codeVoice","code":"Vigram.Logger(url:mode:)"},{"text":".","type":"text"}],"type":"paragraph"}]},{"content":[{"inlineContent":[{"text":"JSON Lines support log format for easier support analysis.","type":"text"}],"type":"paragraph"}]},{"content":[{"inlineContent":[{"text":"Automatic NTRIP reconnect, enabled by default.","type":"text"}],"type":"paragraph"}]},{"content":[{"inlineContent":[{"text":"NTRIP reconnect progress states.","type":"text"}],"type":"paragraph"}]},{"content":[{"inlineContent":[{"text":"Separate HTTPS flags for NTRIP mountpoints and correction stream.","type":"text"}],"type":"paragraph"}]},{"content":[{"inlineContent":[{"text":"Separate NTRIP mountpoint timeout: ","type":"text"},{"type":"codeVoice","code":"Configuration.ntripMountpointsTimeout"},{"text":".","type":"text"}],"type":"paragraph"}]}],"type":"unorderedList"},{"level":2,"text":"Changed","anchor":"Changed","type":"heading"},{"items":[{"content":[{"inlineContent":[{"text":"Peripheral startup and configuration are more stable.","type":"text"}],"type":"paragraph"}]},{"content":[{"inlineContent":[{"text":"BLE writes are coordinated sequentially, making concurrent send operations safer.","type":"text"}],"type":"paragraph"}]},{"content":[{"inlineContent":[{"text":"GPS and NTRIP correction state handling is more resilient.","type":"text"}],"type":"paragraph"}]},{"content":[{"inlineContent":[{"text":"Minimum Swift version in documentation is now Swift 5.7.","type":"text"}],"type":"paragraph"}]}],"type":"unorderedList"},{"level":2,"text":"Fixed And Improved","anchor":"Fixed-And-Improved","type":"heading"},{"items":[{"content":[{"inlineContent":[{"text":"Improved error handling and support diagnostics around Bluetooth, peripheral startup, GPS and NTRIP.","type":"text"}],"type":"paragraph"}]},{"content":[{"inlineContent":[{"text":"Improved NMEA, device, peripheral and satellite parsing.","type":"text"}],"type":"paragraph"}]},{"content":[{"inlineContent":[{"text":"Improved Single Point diagnostics for invalid data, low accuracy, bad laser quality, duplicate sessions and cancellation.","type":"text"}],"type":"paragraph"}]},{"content":[{"inlineContent":[{"text":"Improved support log privacy by redacting credentials, tokens and private device identifiers.","type":"text"}],"type":"paragraph"}]},{"content":[{"inlineContent":[{"text":"Improved NTRIP debug descriptions by redacting credentials.","type":"text"}],"type":"paragraph"}]},{"content":[{"inlineContent":[{"text":"Minor bug fix.","type":"text"}],"type":"paragraph"}]}],"type":"unorderedList"}]}],"variants":[{"traits":[{"interfaceLanguage":"swift"}],"paths":["\/documentation\/vigramsdk\/2.0.0-beta"]}],"metadata":{"modules":[{"name":"VigramSDK"}],"title":"2.0.0-beta","role":"article","roleHeading":"Article","images":[{"identifier":"logo.png","type":"icon"}]},"kind":"article","sections":[],"schemaVersion":{"minor":3,"major":0,"patch":0},"identifier":{"url":"doc:\/\/com.vigramsdk\/documentation\/VigramSDK\/2.0.0-beta","interfaceLanguage":"swift"},"hierarchy":{"paths":[["doc:\/\/com.vigramsdk\/documentation\/VigramSDK"]]},"references":{"doc://com.vigramsdk/documentation/VigramSDK":{"kind":"symbol","images":[{"identifier":"logo.png","type":"icon"}],"type":"topic","role":"collection","abstract":[],"url":"\/documentation\/vigramsdk","identifier":"doc:\/\/com.vigramsdk\/documentation\/VigramSDK","title":"VigramSDK"},"logo.png":{"variants":[{"url":"\/images\/com.vigramsdk\/logo.png","traits":["1x","light"]}],"alt":"Vigram logo.","type":"image","identifier":"logo.png"}}}